openbb_yfinance/__init__.py
openbb_yfinance/models/__init__.py
openbb_yfinance/models/active.py
openbb_yfinance/models/aggressive_small_caps.py
openbb_yfinance/models/available_indices.py
openbb_yfinance/models/balance_sheet.py
openbb_yfinance/models/cash_flow.py
openbb_yfinance/models/company_news.py
openbb_yfinance/models/crypto_historical.py
openbb_yfinance/models/currency_historical.py
openbb_yfinance/models/equity_historical.py
openbb_yfinance/models/equity_profile.py
openbb_yfinance/models/equity_quote.py
openbb_yfinance/models/equity_screener.py
openbb_yfinance/models/etf_info.py
openbb_yfinance/models/futures_curve.py
openbb_yfinance/models/futures_historical.py
openbb_yfinance/models/gainers.py
openbb_yfinance/models/growth_tech_equities.py
openbb_yfinance/models/historical_dividends.py
openbb_yfinance/models/income_statement.py
openbb_yfinance/models/index_historical.py
openbb_yfinance/models/key_executives.py
openbb_yfinance/models/key_metrics.py
openbb_yfinance/models/losers.py
openbb_yfinance/models/options_chains.py
openbb_yfinance/models/price_target_consensus.py
openbb_yfinance/models/share_statistics.py
openbb_yfinance/models/undervalued_growth_equities.py
openbb_yfinance/models/undervalued_large_caps.py
openbb_yfinance/py.typed
openbb_yfinance/utils/__init__.py
openbb_yfinance/utils/futures.csv
openbb_yfinance/utils/helpers.py
openbb_yfinance/utils/references.py
openbb_yfinance-1.5.1.dist-info/METADATA
openbb_yfinance-1.5.1.dist-info/WHEEL
openbb_yfinance-1.5.1.dist-info/entry_points.txt
openbb_yfinance-1.5.1.dist-info/RECORD
